radar_models/__init__.py
radar_models/radar2.py
radar_models/radar3.py
radar_models-1.1.2.dist-info/LICENSE
radar_models-1.1.2.dist-info/METADATA
radar_models-1.1.2.dist-info/WHEEL
radar_models-1.1.2.dist-info/RECORD
